{
	"animations": [
		{
			"offsets": [
				-20,
				200
			],
			"loop": false,
			"fps": 24,
			"anim": "singLEFT",
			"indices": [],
			"name": "l"
		},
		{
			"offsets": [
				-30,
				220
			],
			"loop": false,
			"fps": 24,
			"anim": "singUP",
			"indices": [],
			"name": "u"
		},
		{
			"offsets": [
				30,
				240
			],
			"loop": false,
			"fps": 24,
			"anim": "singRIGHT",
			"indices": [],
			"name": "r"
		},
		{
			"offsets": [
				20,
				180
			],
			"loop": false,
			"fps": 30,
			"anim": "singDOWN",
			"indices": [],
			"name": "d"
		},
		{
			"offsets": [
				0,
				0
			],
			"indices": [],
			"fps": 12,
			"anim": "idle",
			"loop": true,
			"name": "i"
		}
	],
	"vocals_file": "",
	"no_antialiasing": false,
	"image": "characters/blev",
	"position": [
		-1720,
		-620
	],
	"healthicon": "blev",
	"flip_x": true,
	"healthbar_colors": [
		0,
		0,
		255
	],
	"camera_position": [
		1420,
		720
	],
	"sing_duration": 4,
	"scale": 0.3,
	"_editor_isPlayer": false
}